{
  "note":"This file contains the actual data for your assignment",
  "comments":[
    {
      "name":"Conli",
      "count":100
    },
    {
      "name":"Kiaya",
      "count":99
    },
    {
      "name":"Marta",
      "count":98
    },
    {
      "name":"Taonga",
      "count":94
    },
    {
      "name":"Seaan",
      "count":93
    },
    {
      "name":"Tessa",
      "count":92
    },
    {
      "name":"Jonson",
      "count":89
    },
    {
      "name":"Kyra",
      "count":88
    },
    {
      "name":"Caylin",
      "count":87
    },
    {
      "name":"Millan",
      "count":82
    },
    {
      "name":"Alan",
      "count":82
    },
    {
      "name":"Marcquis",
      "count":79
    },
    {
      "name":"Meili",
      "count":72
    },
    {
      "name":"Shafaq",
      "count":70
    },
    {
      "name":"Razan",
      "count":70
    },
    {
      "name":"Rovia",
      "count":68
    },
    {
      "name":"Josephina",
      "count":66
    },
    {
      "name":"Eilean",
      "count":64
    },
    {
      "name":"Rheanne",
      "count":58
    },
    {
      "name":"Nairne",
      "count":58
    },
    {
      "name":"Marc",
      "count":57
    },
    {
      "name":"Marla",
      "count":55
    },
    {
      "name":"Baley",
      "count":54
    },
    {
      "name":"Si",
      "count":52
    },
    {
      "name":"Kianna",
      "count":51
    },
    {
      "name":"Katelyne",
      "count":48
    },
    {
      "name":"Laurie",
      "count":48
    },
    {
      "name":"Zanab",
      "count":46
    },
    {
      "name":"Rhya",
      "count":43
    },
    {
      "name":"Aaryan",
      "count":39
    },
    {
      "name":"Ammara",
      "count":38
    },
    {
      "name":"Katelyn",
      "count":37
    },
    {
      "name":"Lotta",
      "count":34
    },
    {
      "name":"Kiarash",
      "count":33
    },
    {
      "name":"Kamron",
      "count":32
    },
    {
      "name":"Raegan",
      "count":29
    },
    {
      "name":"Hopkin",
      "count":29
    },
    {
      "name":"Krystyna",
      "count":27
    },
    {
      "name":"Makaila",
      "count":27
    },
    {
      "name":"Kaileb",
      "count":26
    },
    {
      "name":"Aurelia",
      "count":25
    },
    {
      "name":"Iona",
      "count":18
    },
    {
      "name":"Veera",
      "count":17
    },
    {
      "name":"Wang",
      "count":17
    },
    {
      "name":"Kamsiyochi",
      "count":12
    },
    {
      "name":"Harrington",
      "count":9
    },
    {
      "name":"Rafif",
      "count":5
    },
    {
      "name":"Gareth",
      "count":2
    },
    {
      "name":"Se",
      "count":2
    },
    {
      "name":"Kristen",
      "count":2
    }
  ]
}